pyostrap/__init__.py
pyostrap/biostrap_api.py
pyostrap/exceptions.py
pyostrap/httpx_adapter.py
pyostrap/util.py
pyostrap-2025.4.11.0.dist-info/METADATA
pyostrap-2025.4.11.0.dist-info/WHEEL
pyostrap-2025.4.11.0.dist-info/licenses/LICENSE
pyostrap-2025.4.11.0.dist-info/RECORD
